sentence_similarity/__init__.py
sentence_similarity/cls_token_embedding.py
sentence_similarity/sentence_embedding.py
sentence_similarity/sentence_similarity.py
sentence_similarity/similarity_functions.py
sentence_similarity-1.0.0.dist-info/METADATA
sentence_similarity-1.0.0.dist-info/RECORD
sentence_similarity-1.0.0.dist-info/WHEEL
sentence_similarity-1.0.0.dist-info/top_level.txt
