Metadata-Version: 2.1
Name: sentence-similarity
Version: 1.0.0
Summary: Package to calculate the similarity score of two sentences
Home-page: https://github.com/Susheel-1999/Sentence_Similarity
Author: Susheel
Author-email: susheelnagesh@gmail.com
License: UNKNOWN
Platform: UNKNOWN
Classifier: Programming Language :: Python :: 3
Classifier: License :: OSI Approved :: MIT License
Classifier: Operating System :: OS Independent
Requires-Python: >=3.6
Requires-Dist: transformers (==4.9.2)
Requires-Dist: sentence-transformers (==2.0.0)
